jove/__init__.py
jove/analysis.py
jove/templates/README.md
jove/templates/jove.py
jove/templates/libjove.py
jove/templates/shell.sh
jove-0.0.6.dist-info/LICENSE
jove-0.0.6.dist-info/METADATA
jove-0.0.6.dist-info/WHEEL
jove-0.0.6.dist-info/entry_points.txt
jove-0.0.6.dist-info/top_level.txt
jove-0.0.6.dist-info/RECORD
