Metadata-Version: 2.2
Name: jove
Version: 0.0.6
Summary: A terminal-focused alternative to Jupyter notebooks.
Home-page: https://github.com/brandtg/jove
Author: Greg Brandt
Author-email: brandt.greg@protonmail.com
License-File: LICENSE
Provides-Extra: dev
Requires-Dist: pytest==8.3.3; extra == "dev"
Requires-Dist: black==24.8.0; extra == "dev"
Dynamic: author
Dynamic: author-email
Dynamic: description
Dynamic: description-content-type
Dynamic: home-page
Dynamic: provides-extra
Dynamic: summary
